omegaid/core/__init__.py
omegaid/core/atoms.py
omegaid/core/decomposition.py
omegaid/core/doublet_lattice.py
omegaid/core/entropy.py
omegaid/utils/__init__.py
omegaid/utils/backend.py
omegaid-0.2.5.dist-info/METADATA
omegaid-0.2.5.dist-info/WHEEL
omegaid-0.2.5.dist-info/licenses/LICENSE
omegaid-0.2.5.dist-info/RECORD
