Metadata-Version: 2.4
Name: omegaid
Version: 0.2.5
Summary: A high-performance toolbox for PhiID computation, accelerated by GPU.
Author-email: Rui Lin <Rui.Lin.ipwt@proton.me>
License: BSD 3-Clause License
License-File: LICENSE
Keywords: cupy,gpu,information theory,pid
Classifier: Development Status :: 3 - Alpha
Classifier: Intended Audience :: Science/Research
Classifier: License :: OSI Approved :: BSD License
Classifier: Programming Language :: Python :: 3 :: Only
Requires-Python: >=3.12
Requires-Dist: numba>=0.58.1
Requires-Dist: numpy
Requires-Dist: scipy
Provides-Extra: cuda-11x
Requires-Dist: cupy-cuda11x; extra == 'cuda-11x'
Provides-Extra: cuda-12x
Requires-Dist: cupy-cuda12x; extra == 'cuda-12x'
